pip_tools_hash-0.0.1.dist-info/DESCRIPTION.rst
pip_tools_hash-0.0.1.dist-info/METADATA
pip_tools_hash-0.0.1.dist-info/RECORD
pip_tools_hash-0.0.1.dist-info/WHEEL
pip_tools_hash-0.0.1.dist-info/entry_points.txt
pip_tools_hash-0.0.1.dist-info/metadata.json
pip_tools_hash-0.0.1.dist-info/top_level.txt
piptools/__init__.py
piptools/__main__.py
piptools/cache.py
piptools/click.py
piptools/exceptions.py
piptools/io.py
piptools/locations.py
piptools/logging.py
piptools/resolver.py
piptools/sync.py
piptools/utils.py
piptools/writer.py
piptools/_compat/__init__.py
piptools/_compat/contextlib.py
piptools/_compat/tempfile.py
piptools/repositories/__init__.py
piptools/repositories/base.py
piptools/repositories/local.py
piptools/repositories/pypi.py
piptools/scripts/__init__.py
piptools/scripts/compile.py
piptools/scripts/sync.py
