Metadata-Version: 2.0
Name: pip-tools-hash
Version: 0.0.1
Summary: 
Requires-Dist: click (>=6)
Requires-Dist: first
Requires-Dist: setuptools
Requires-Dist: six
